discordrp_pcsx2/__init__.py
discordrp_pcsx2/utils.py
discordrp_pcsx2-0.1.0.dist-info/entry_points.txt
discordrp_pcsx2-0.1.0.dist-info/WHEEL
discordrp_pcsx2-0.1.0.dist-info/METADATA
discordrp_pcsx2-0.1.0.dist-info/RECORD
